{
    "point_count": 641,
    "points": [
        {
            "x": 2551.9375,
            "y": 2535.3125
        },
        {
            "x": 1812.125,
            "y": 2493.75
        },
        {
            "x": 2069.8125,
            "y": 2684.9375
        },
        {
            "x": 2069.8125,
            "y": 2651.6875
        },
        {
            "x": 1953.4375,
            "y": 2643.375
        },
        {
            "x": 1945.125,
            "y": 2668.3125
        },
        {
            "x": 2028.25,
            "y": 2826.25
        },
        {
            "x": 2028.25,
            "y": 2851.1875
        },
        {
            "x": 1995.0,
            "y": 2734.8125
        },
        {
            "x": 2011.625,
            "y": 2734.8125
        },
        {
            "x": 2003.3125,
            "y": 2751.4375
        },
        {
            "x": 2144.625,
            "y": 2560.25
        },
        {
            "x": 2136.3125,
            "y": 2568.5625
        },
        {
            "x": 1911.875,
            "y": 2518.6875
        },
        {
            "x": 1911.875,
            "y": 2527.0
        },
        {
            "x": 1845.375,
            "y": 2684.9375
        },
        {
            "x": 1820.4375,
            "y": 2684.9375
        },
        {
            "x": 1928.5,
            "y": 2643.375
        },
        {
            "x": 1928.5,
            "y": 2660.0
        },
        {
            "x": 1920.1875,
            "y": 2660.0
        },
        {
            "x": 1986.6875,
            "y": 2668.3125
        },
        {
            "x": 1986.6875,
            "y": 2660.0
        },
        {
            "x": 2003.3125,
            "y": 2684.9375
        },
        {
            "x": 1995.0,
            "y": 2684.9375
        },
        {
            "x": 2211.125,
            "y": 2485.4375
        },
        {
            "x": 1554.4375,
            "y": 2668.3125
        },
        {
            "x": 2136.3125,
            "y": 3059.0
        },
        {
            "x": 2743.125,
            "y": 2568.5625
        },
        {
            "x": 2635.0625,
            "y": 2493.75
        },
        {
            "x": 2684.9375,
            "y": 2718.1875
        },
        {
            "x": 2726.5,
            "y": 2743.125
        },
        {
            "x": 2701.5625,
            "y": 2743.125
        },
        {
            "x": 1745.625,
            "y": 2335.8125
        },
        {
            "x": 1737.3125,
            "y": 2352.4375
        },
        {
            "x": 1662.5,
            "y": 2302.5625
        },
        {
            "x": 1554.4375,
            "y": 2618.4375
        },
        {
            "x": 1562.75,
            "y": 2618.4375
        },
        {
            "x": 1687.4375,
            "y": 2227.75
        },
        {
            "x": 1645.875,
            "y": 2285.9375
        },
        {
            "x": 1629.25,
            "y": 2194.5
        },
        {
            "x": 1712.375,
            "y": 2244.375
        },
        {
            "x": 1662.5,
            "y": 2277.625
        },
        {
            "x": 2651.6875,
            "y": 2684.9375
        },
        {
            "x": 2651.6875,
            "y": 2651.6875
        },
        {
            "x": 2668.3125,
            "y": 2651.6875
        },
        {
            "x": 2668.3125,
            "y": 2684.9375
        },
        {
            "x": 1587.6875,
            "y": 3632.5625
        },
        {
            "x": 1546.125,
            "y": 3591.0
        },
        {
            "x": 1704.0625,
            "y": 3316.6875
        },
        {
            "x": 1828.75,
            "y": 3665.8125
        },
        {
            "x": 1704.0625,
            "y": 3308.375
        },
        {
            "x": 1787.1875,
            "y": 3657.5
        },
        {
            "x": 2011.625,
            "y": 3582.6875
        },
        {
            "x": 1753.9375,
            "y": 3108.875
        },
        {
            "x": 1778.875,
            "y": 3075.625
        },
        {
            "x": 1787.1875,
            "y": 3067.3125
        },
        {
            "x": 1778.875,
            "y": 3499.5625
        },
        {
            "x": 1787.1875,
            "y": 3532.8125
        },
        {
            "x": 1812.125,
            "y": 3566.0625
        },
        {
            "x": 1720.6875,
            "y": 3524.5
        },
        {
            "x": 1762.25,
            "y": 3524.5
        },
        {
            "x": 1762.25,
            "y": 3507.875
        },
        {
            "x": 2593.5,
            "y": 2784.6875
        },
        {
            "x": 2369.0625,
            "y": 3316.6875
        },
        {
            "x": 2377.375,
            "y": 3325.0
        },
        {
            "x": 2302.5625,
            "y": 3250.1875
        },
        {
            "x": 2319.1875,
            "y": 3258.5
        },
        {
            "x": 2601.8125,
            "y": 2975.875
        },
        {
            "x": 2593.5,
            "y": 2959.25
        },
        {
            "x": 2668.3125,
            "y": 3034.0625
        },
        {
            "x": 2660.0,
            "y": 3025.75
        },
        {
            "x": 2527.0,
            "y": 3167.0625
        },
        {
            "x": 2510.375,
            "y": 3183.6875
        },
        {
            "x": 2443.875,
            "y": 3117.1875
        },
        {
            "x": 2460.5,
            "y": 3100.5625
        },
        {
            "x": 2768.0625,
            "y": 2859.5
        },
        {
            "x": 2784.6875,
            "y": 2909.375
        },
        {
            "x": 2285.9375,
            "y": 3050.6875
        },
        {
            "x": 2734.8125,
            "y": 3092.25
        },
        {
            "x": 2277.625,
            "y": 3059.0
        },
        {
            "x": 2269.3125,
            "y": 3067.3125
        },
        {
            "x": 2410.625,
            "y": 2926.0
        },
        {
            "x": 2402.3125,
            "y": 2934.3125
        },
        {
            "x": 2394.0,
            "y": 2942.625
        },
        {
            "x": 2726.5,
            "y": 3117.1875
        },
        {
            "x": 2718.1875,
            "y": 3100.5625
        },
        {
            "x": 2543.625,
            "y": 2784.6875
        },
        {
            "x": 2169.5625,
            "y": 3366.5625
        },
        {
            "x": 2161.25,
            "y": 3358.25
        },
        {
            "x": 2793.0,
            "y": 2277.625
        },
        {
            "x": 2851.1875,
            "y": 2285.9375
        },
        {
            "x": 2817.9375,
            "y": 2244.375
        },
        {
            "x": 2660.0,
            "y": 1662.5
        },
        {
            "x": 2219.4375,
            "y": 1911.875
        },
        {
            "x": 2211.125,
            "y": 1911.875
        },
        {
            "x": 2660.0,
            "y": 1679.125
        },
        {
            "x": 2618.4375,
            "y": 1670.8125
        },
        {
            "x": 2369.0625,
            "y": 1820.4375
        },
        {
            "x": 2385.6875,
            "y": 1812.125
        },
        {
            "x": 2410.625,
            "y": 1828.75
        },
        {
            "x": 2527.0,
            "y": 1770.5625
        },
        {
            "x": 2418.9375,
            "y": 1637.5625
        },
        {
            "x": 2418.9375,
            "y": 1654.1875
        },
        {
            "x": 2418.9375,
            "y": 1662.5
        },
        {
            "x": 2418.9375,
            "y": 1670.8125
        },
        {
            "x": 2152.9375,
            "y": 2211.125
        },
        {
            "x": 2136.3125,
            "y": 2219.4375
        },
        {
            "x": 2103.0625,
            "y": 2169.5625
        },
        {
            "x": 2468.8125,
            "y": 1945.125
        },
        {
            "x": 2477.125,
            "y": 1953.4375
        },
        {
            "x": 2402.3125,
            "y": 1679.125
        },
        {
            "x": 2402.3125,
            "y": 1637.5625
        },
        {
            "x": 2418.9375,
            "y": 1679.125
        },
        {
            "x": 2344.125,
            "y": 1670.8125
        },
        {
            "x": 2344.125,
            "y": 1654.1875
        },
        {
            "x": 2502.0625,
            "y": 1654.1875
        },
        {
            "x": 2502.0625,
            "y": 1662.5
        },
        {
            "x": 2527.0,
            "y": 1795.5
        },
        {
            "x": 2244.375,
            "y": 1554.4375
        },
        {
            "x": 2585.1875,
            "y": 1870.3125
        },
        {
            "x": 2269.3125,
            "y": 1654.1875
        },
        {
            "x": 2269.3125,
            "y": 1670.8125
        },
        {
            "x": 2227.75,
            "y": 1654.1875
        },
        {
            "x": 2227.75,
            "y": 1662.5
        },
        {
            "x": 2227.75,
            "y": 1670.8125
        },
        {
            "x": 2227.75,
            "y": 1645.875
        },
        {
            "x": 2427.25,
            "y": 1753.9375
        },
        {
            "x": 2435.5625,
            "y": 1737.3125
        },
        {
            "x": 814.625,
            "y": 1687.4375
        },
        {
            "x": 839.5625,
            "y": 1687.4375
        },
        {
            "x": 822.9375,
            "y": 1729.0
        },
        {
            "x": 847.875,
            "y": 1679.125
        },
        {
            "x": 806.3125,
            "y": 1679.125
        },
        {
            "x": 847.875,
            "y": 1620.9375
        },
        {
            "x": 806.3125,
            "y": 1620.9375
        },
        {
            "x": 748.125,
            "y": 1487.9375
        },
        {
            "x": 781.375,
            "y": 1487.9375
        },
        {
            "x": 764.75,
            "y": 1537.8125
        },
        {
            "x": 789.6875,
            "y": 1487.9375
        },
        {
            "x": 748.125,
            "y": 1487.9375
        },
        {
            "x": 922.6875,
            "y": 1712.375
        },
        {
            "x": 931.0,
            "y": 1720.6875
        },
        {
            "x": 706.5625,
            "y": 1712.375
        },
        {
            "x": 748.125,
            "y": 1729.0
        },
        {
            "x": 698.25,
            "y": 1679.125
        },
        {
            "x": 906.0625,
            "y": 1521.1875
        },
        {
            "x": 872.8125,
            "y": 1479.625
        },
        {
            "x": 856.1875,
            "y": 1878.625
        },
        {
            "x": 914.375,
            "y": 1878.625
        },
        {
            "x": 1454.6875,
            "y": 1803.8125
        },
        {
            "x": 822.9375,
            "y": 1828.75
        },
        {
            "x": 831.25,
            "y": 1853.6875
        },
        {
            "x": 1438.0625,
            "y": 1812.125
        },
        {
            "x": 739.8125,
            "y": 1321.6875
        },
        {
            "x": 739.8125,
            "y": 1330.0
        },
        {
            "x": 731.5,
            "y": 1305.0625
        },
        {
            "x": 731.5,
            "y": 1346.625
        },
        {
            "x": 598.5,
            "y": 1354.9375
        },
        {
            "x": 598.5,
            "y": 1296.75
        },
        {
            "x": 1820.4375,
            "y": 2053.1875
        },
        {
            "x": 1895.25,
            "y": 2111.375
        },
        {
            "x": 1421.4375,
            "y": 1928.5
        },
        {
            "x": 1604.3125,
            "y": 1986.6875
        },
        {
            "x": 1512.875,
            "y": 1961.75
        },
        {
            "x": 1537.8125,
            "y": 1878.625
        },
        {
            "x": 1554.4375,
            "y": 1878.625
        },
        {
            "x": 1479.625,
            "y": 2028.25
        },
        {
            "x": 1388.1875,
            "y": 1970.0625
        },
        {
            "x": 1629.25,
            "y": 1903.5625
        },
        {
            "x": 1612.625,
            "y": 1886.9375
        },
        {
            "x": 1637.5625,
            "y": 1878.625
        },
        {
            "x": 1396.5,
            "y": 1986.6875
        },
        {
            "x": 1413.125,
            "y": 1928.5
        },
        {
            "x": 1529.5,
            "y": 1953.4375
        },
        {
            "x": 1521.1875,
            "y": 1945.125
        },
        {
            "x": 1604.3125,
            "y": 1995.0
        },
        {
            "x": 1512.875,
            "y": 2011.625
        },
        {
            "x": 1504.5625,
            "y": 2036.5625
        },
        {
            "x": 1180.375,
            "y": 2510.375
        },
        {
            "x": 1122.1875,
            "y": 2518.6875
        },
        {
            "x": 1097.25,
            "y": 2510.375
        },
        {
            "x": 1213.625,
            "y": 2518.6875
        },
        {
            "x": 1188.6875,
            "y": 2543.625
        },
        {
            "x": 1338.3125,
            "y": 2651.6875
        },
        {
            "x": 847.875,
            "y": 2169.5625
        },
        {
            "x": 814.625,
            "y": 2161.25
        },
        {
            "x": 773.0625,
            "y": 2103.0625
        },
        {
            "x": 748.125,
            "y": 2094.75
        },
        {
            "x": 889.4375,
            "y": 2169.5625
        },
        {
            "x": 881.125,
            "y": 2152.9375
        },
        {
            "x": 872.8125,
            "y": 2169.5625
        },
        {
            "x": 872.8125,
            "y": 2128.0
        },
        {
            "x": 847.875,
            "y": 2111.375
        },
        {
            "x": 931.0,
            "y": 2369.0625
        },
        {
            "x": 1030.75,
            "y": 2369.0625
        },
        {
            "x": 964.25,
            "y": 2285.9375
        },
        {
            "x": 1022.4375,
            "y": 2036.5625
        },
        {
            "x": 1039.0625,
            "y": 2144.625
        },
        {
            "x": 964.25,
            "y": 2111.375
        },
        {
            "x": 1005.8125,
            "y": 2086.4375
        },
        {
            "x": 773.0625,
            "y": 2261.0
        },
        {
            "x": 739.8125,
            "y": 2252.6875
        },
        {
            "x": 748.125,
            "y": 2277.625
        },
        {
            "x": 1280.125,
            "y": 2219.4375
        },
        {
            "x": 1088.9375,
            "y": 2285.9375
        },
        {
            "x": 1263.5,
            "y": 2161.25
        },
        {
            "x": 1363.25,
            "y": 2211.125
        },
        {
            "x": 1072.3125,
            "y": 2302.5625
        },
        {
            "x": 1072.3125,
            "y": 2285.9375
        },
        {
            "x": 1305.0625,
            "y": 2543.625
        },
        {
            "x": 1296.75,
            "y": 2535.3125
        },
        {
            "x": 1288.4375,
            "y": 2543.625
        },
        {
            "x": 1338.3125,
            "y": 2352.4375
        },
        {
            "x": 1305.0625,
            "y": 2352.4375
        },
        {
            "x": 1338.3125,
            "y": 2360.75
        },
        {
            "x": 1413.125,
            "y": 2452.1875
        },
        {
            "x": 1413.125,
            "y": 2626.75
        },
        {
            "x": 1404.8125,
            "y": 2626.75
        },
        {
            "x": 1338.3125,
            "y": 2618.4375
        },
        {
            "x": 1296.75,
            "y": 2418.9375
        },
        {
            "x": 1454.6875,
            "y": 2493.75
        },
        {
            "x": 1404.8125,
            "y": 2493.75
        },
        {
            "x": 1346.625,
            "y": 2468.8125
        },
        {
            "x": 1330.0,
            "y": 2452.1875
        },
        {
            "x": 1363.25,
            "y": 2435.5625
        },
        {
            "x": 1463.0,
            "y": 2485.4375
        },
        {
            "x": 1205.3125,
            "y": 2410.625
        },
        {
            "x": 1188.6875,
            "y": 2410.625
        },
        {
            "x": 1321.6875,
            "y": 2651.6875
        },
        {
            "x": 1330.0,
            "y": 2660.0
        },
        {
            "x": 1205.3125,
            "y": 2402.3125
        },
        {
            "x": 1429.75,
            "y": 3541.125
        },
        {
            "x": 1446.375,
            "y": 3549.4375
        },
        {
            "x": 1446.375,
            "y": 3532.8125
        },
        {
            "x": 906.0625,
            "y": 3042.375
        },
        {
            "x": 889.4375,
            "y": 3075.625
        },
        {
            "x": 939.3125,
            "y": 3025.75
        },
        {
            "x": 1180.375,
            "y": 3524.5
        },
        {
            "x": 798.0,
            "y": 3383.1875
        },
        {
            "x": 1629.25,
            "y": 3125.5
        },
        {
            "x": 1230.25,
            "y": 2984.1875
        },
        {
            "x": 1130.5,
            "y": 2984.1875
        },
        {
            "x": 1221.9375,
            "y": 3241.875
        },
        {
            "x": 1130.5,
            "y": 3241.875
        },
        {
            "x": 1197.0,
            "y": 3108.875
        },
        {
            "x": 1163.75,
            "y": 3092.25
        },
        {
            "x": 1197.0,
            "y": 3092.25
        },
        {
            "x": 1163.75,
            "y": 3108.875
        },
        {
            "x": 1055.6875,
            "y": 3117.1875
        },
        {
            "x": 1014.125,
            "y": 3075.625
        },
        {
            "x": 1130.5,
            "y": 3216.9375
        },
        {
            "x": 1147.125,
            "y": 3225.25
        },
        {
            "x": 1221.9375,
            "y": 3216.9375
        },
        {
            "x": 1205.3125,
            "y": 3225.25
        },
        {
            "x": 1246.875,
            "y": 3291.75
        },
        {
            "x": 1271.8125,
            "y": 3349.9375
        },
        {
            "x": 1005.8125,
            "y": 3441.375
        },
        {
            "x": 989.1875,
            "y": 3424.75
        },
        {
            "x": 980.875,
            "y": 3408.125
        },
        {
            "x": 756.4375,
            "y": 3349.9375
        },
        {
            "x": 931.0,
            "y": 3358.25
        },
        {
            "x": 798.0,
            "y": 3507.875
        },
        {
            "x": 1271.8125,
            "y": 3433.0625
        },
        {
            "x": 1271.8125,
            "y": 3449.6875
        },
        {
            "x": 1238.5625,
            "y": 3449.6875
        },
        {
            "x": 822.9375,
            "y": 2635.0625
        },
        {
            "x": 814.625,
            "y": 2618.4375
        },
        {
            "x": 847.875,
            "y": 2618.4375
        },
        {
            "x": 947.625,
            "y": 3183.6875
        },
        {
            "x": 955.9375,
            "y": 3158.75
        },
        {
            "x": 1479.625,
            "y": 2901.0625
        },
        {
            "x": 1413.125,
            "y": 2884.4375
        },
        {
            "x": 1454.6875,
            "y": 3042.375
        },
        {
            "x": 1454.6875,
            "y": 3034.0625
        },
        {
            "x": 1579.375,
            "y": 3017.4375
        },
        {
            "x": 1604.3125,
            "y": 3017.4375
        },
        {
            "x": 1313.375,
            "y": 3108.875
        },
        {
            "x": 1313.375,
            "y": 3100.5625
        },
        {
            "x": 1172.0625,
            "y": 2975.875
        },
        {
            "x": 1180.375,
            "y": 2975.875
        },
        {
            "x": 1388.1875,
            "y": 2876.125
        },
        {
            "x": 1155.4375,
            "y": 2842.875
        },
        {
            "x": 1205.3125,
            "y": 2842.875
        },
        {
            "x": 1047.375,
            "y": 2909.375
        },
        {
            "x": 1039.0625,
            "y": 2909.375
        },
        {
            "x": 1105.5625,
            "y": 2876.125
        },
        {
            "x": 1064.0,
            "y": 3100.5625
        },
        {
            "x": 1188.6875,
            "y": 3050.6875
        },
        {
            "x": 1163.75,
            "y": 3050.6875
        },
        {
            "x": 1188.6875,
            "y": 3150.4375
        },
        {
            "x": 1163.75,
            "y": 3150.4375
        },
        {
            "x": 831.25,
            "y": 2610.125
        },
        {
            "x": 2784.6875,
            "y": 3740.625
        },
        {
            "x": 2793.0,
            "y": 3724.0
        },
        {
            "x": 2776.375,
            "y": 3724.0
        },
        {
            "x": 3009.125,
            "y": 3956.75
        },
        {
            "x": 3050.6875,
            "y": 3898.5625
        },
        {
            "x": 3075.625,
            "y": 3948.4375
        },
        {
            "x": 3059.0,
            "y": 3973.375
        },
        {
            "x": 3059.0,
            "y": 3832.0625
        },
        {
            "x": 3034.0625,
            "y": 3840.375
        },
        {
            "x": 2942.625,
            "y": 3956.75
        },
        {
            "x": 2942.625,
            "y": 3973.375
        },
        {
            "x": 3092.25,
            "y": 3998.3125
        },
        {
            "x": 3108.875,
            "y": 3973.375
        },
        {
            "x": 2975.875,
            "y": 4181.1875
        },
        {
            "x": 2975.875,
            "y": 4189.5
        },
        {
            "x": 2693.25,
            "y": 4147.9375
        },
        {
            "x": 2693.25,
            "y": 4073.125
        },
        {
            "x": 2643.375,
            "y": 4114.6875
        },
        {
            "x": 2726.5,
            "y": 4114.6875
        },
        {
            "x": 2369.0625,
            "y": 3699.0625
        },
        {
            "x": 2385.6875,
            "y": 3724.0
        },
        {
            "x": 2202.8125,
            "y": 3773.875
        },
        {
            "x": 2285.9375,
            "y": 3707.375
        },
        {
            "x": 2518.6875,
            "y": 3773.875
        },
        {
            "x": 2502.0625,
            "y": 3773.875
        },
        {
            "x": 2510.375,
            "y": 3757.25
        },
        {
            "x": 2261.0,
            "y": 3973.375
        },
        {
            "x": 2244.375,
            "y": 3965.0625
        },
        {
            "x": 2261.0,
            "y": 3956.75
        },
        {
            "x": 2202.8125,
            "y": 3815.4375
        },
        {
            "x": 2202.8125,
            "y": 3898.5625
        },
        {
            "x": 2294.25,
            "y": 4014.9375
        },
        {
            "x": 2310.875,
            "y": 3823.75
        },
        {
            "x": 2344.125,
            "y": 3832.0625
        },
        {
            "x": 2319.1875,
            "y": 3857.0
        },
        {
            "x": 2402.3125,
            "y": 4014.9375
        },
        {
            "x": 2510.375,
            "y": 3906.875
        },
        {
            "x": 2269.3125,
            "y": 3682.4375
        },
        {
            "x": 2510.375,
            "y": 3458.0
        },
        {
            "x": 1055.6875,
            "y": 1064.0
        },
        {
            "x": 1064.0,
            "y": 1080.625
        },
        {
            "x": 947.625,
            "y": 897.75
        },
        {
            "x": 931.0,
            "y": 1047.375
        },
        {
            "x": 931.0,
            "y": 1080.625
        },
        {
            "x": 947.625,
            "y": 1072.3125
        },
        {
            "x": 922.6875,
            "y": 897.75
        },
        {
            "x": 1363.25,
            "y": 1604.3125
        },
        {
            "x": 1321.6875,
            "y": 1645.875
        },
        {
            "x": 1313.375,
            "y": 1446.375
        },
        {
            "x": 1296.75,
            "y": 1429.75
        },
        {
            "x": 1305.0625,
            "y": 1413.125
        },
        {
            "x": 1321.6875,
            "y": 1429.75
        },
        {
            "x": 1396.5,
            "y": 1429.75
        },
        {
            "x": 1413.125,
            "y": 1429.75
        },
        {
            "x": 1371.5625,
            "y": 1454.6875
        },
        {
            "x": 1263.5,
            "y": 1695.75
        },
        {
            "x": 1246.875,
            "y": 1695.75
        },
        {
            "x": 1188.6875,
            "y": 1670.8125
        },
        {
            "x": 1080.625,
            "y": 1562.75
        },
        {
            "x": 1088.9375,
            "y": 1562.75
        },
        {
            "x": 1246.875,
            "y": 1338.3125
        },
        {
            "x": 1255.1875,
            "y": 1305.0625
        },
        {
            "x": 1113.875,
            "y": 1438.0625
        },
        {
            "x": 1155.4375,
            "y": 1396.5
        },
        {
            "x": 1704.0625,
            "y": 1288.4375
        },
        {
            "x": 1729.0,
            "y": 1246.875
        },
        {
            "x": 1512.875,
            "y": 1454.6875
        },
        {
            "x": 1720.6875,
            "y": 1421.4375
        },
        {
            "x": 1787.1875,
            "y": 1379.875
        },
        {
            "x": 1787.1875,
            "y": 1396.5
        },
        {
            "x": 1745.625,
            "y": 1421.4375
        },
        {
            "x": 748.125,
            "y": 980.875
        },
        {
            "x": 781.375,
            "y": 789.6875
        },
        {
            "x": 756.4375,
            "y": 789.6875
        },
        {
            "x": 723.1875,
            "y": 989.1875
        },
        {
            "x": 739.8125,
            "y": 1005.8125
        },
        {
            "x": 789.6875,
            "y": 980.875
        },
        {
            "x": 764.75,
            "y": 773.0625
        },
        {
            "x": 1305.0625,
            "y": 1346.625
        },
        {
            "x": 1039.0625,
            "y": 1479.625
        },
        {
            "x": 1022.4375,
            "y": 1471.3125
        },
        {
            "x": 1039.0625,
            "y": 1463.0
        },
        {
            "x": 1238.5625,
            "y": 1330.0
        },
        {
            "x": 1188.6875,
            "y": 980.875
        },
        {
            "x": 1296.75,
            "y": 739.8125
        },
        {
            "x": 1429.75,
            "y": 706.5625
        },
        {
            "x": 1554.4375,
            "y": 714.875
        },
        {
            "x": 1587.6875,
            "y": 665.0
        },
        {
            "x": 997.5,
            "y": 465.5
        },
        {
            "x": 1005.8125,
            "y": 457.1875
        },
        {
            "x": 1221.9375,
            "y": 1064.0
        },
        {
            "x": 1712.375,
            "y": 756.4375
        },
        {
            "x": 1612.625,
            "y": 964.25
        },
        {
            "x": 1263.5,
            "y": 781.375
        },
        {
            "x": 1230.25,
            "y": 814.625
        },
        {
            "x": 1546.125,
            "y": 822.9375
        },
        {
            "x": 1546.125,
            "y": 881.125
        },
        {
            "x": 1487.9375,
            "y": 881.125
        },
        {
            "x": 1487.9375,
            "y": 822.9375
        },
        {
            "x": 1213.625,
            "y": 906.0625
        },
        {
            "x": 1546.125,
            "y": 1147.125
        },
        {
            "x": 1787.1875,
            "y": 914.375
        },
        {
            "x": 2867.8125,
            "y": 3216.9375
        },
        {
            "x": 2859.5,
            "y": 3025.75
        },
        {
            "x": 2776.375,
            "y": 3233.5625
        },
        {
            "x": 2859.5,
            "y": 3017.4375
        },
        {
            "x": 2793.0,
            "y": 3399.8125
        },
        {
            "x": 2809.625,
            "y": 3391.5
        },
        {
            "x": 2793.0,
            "y": 3383.1875
        },
        {
            "x": 3341.625,
            "y": 2535.3125
        },
        {
            "x": 3325.0,
            "y": 2543.625
        },
        {
            "x": 3549.4375,
            "y": 2394.0
        },
        {
            "x": 3541.125,
            "y": 2418.9375
        },
        {
            "x": 3532.8125,
            "y": 2394.0
        },
        {
            "x": 3449.6875,
            "y": 2684.9375
        },
        {
            "x": 3424.75,
            "y": 2684.9375
        },
        {
            "x": 3424.75,
            "y": 2668.3125
        },
        {
            "x": 3275.125,
            "y": 2302.5625
        },
        {
            "x": 3275.125,
            "y": 2285.9375
        },
        {
            "x": 3258.5,
            "y": 2302.5625
        },
        {
            "x": 3258.5,
            "y": 2285.9375
        },
        {
            "x": 3399.8125,
            "y": 2294.25
        },
        {
            "x": 3175.375,
            "y": 2294.25
        },
        {
            "x": 3416.4375,
            "y": 2377.375
        },
        {
            "x": 3383.1875,
            "y": 2377.375
        },
        {
            "x": 3158.75,
            "y": 2186.1875
        },
        {
            "x": 3192.0,
            "y": 2186.1875
        },
        {
            "x": 3308.375,
            "y": 2194.5
        },
        {
            "x": 3482.9375,
            "y": 2119.6875
        },
        {
            "x": 3441.375,
            "y": 2119.6875
        },
        {
            "x": 3333.3125,
            "y": 2194.5
        },
        {
            "x": 3665.8125,
            "y": 1745.625
        },
        {
            "x": 3300.0625,
            "y": 1720.6875
        },
        {
            "x": 3300.0625,
            "y": 1695.75
        },
        {
            "x": 3408.125,
            "y": 1521.1875
        },
        {
            "x": 3391.5,
            "y": 1271.8125
        },
        {
            "x": 3192.0,
            "y": 2011.625
        },
        {
            "x": 3108.875,
            "y": 2103.0625
        },
        {
            "x": 3034.0625,
            "y": 2036.5625
        },
        {
            "x": 3042.375,
            "y": 2003.3125
        },
        {
            "x": 3117.1875,
            "y": 2019.9375
        },
        {
            "x": 3108.875,
            "y": 2011.625
        },
        {
            "x": 3117.1875,
            "y": 2011.625
        },
        {
            "x": 3374.875,
            "y": 1712.375
        },
        {
            "x": 3300.0625,
            "y": 1712.375
        },
        {
            "x": 3341.625,
            "y": 1729.0
        },
        {
            "x": 3333.3125,
            "y": 1695.75
        },
        {
            "x": 3366.5625,
            "y": 1695.75
        },
        {
            "x": 3025.75,
            "y": 1720.6875
        },
        {
            "x": 3025.75,
            "y": 1704.0625
        },
        {
            "x": 3042.375,
            "y": 1729.0
        },
        {
            "x": 3374.875,
            "y": 1704.0625
        },
        {
            "x": 3374.875,
            "y": 1695.75
        },
        {
            "x": 3607.625,
            "y": 1753.9375
        },
        {
            "x": 3607.625,
            "y": 1737.3125
        },
        {
            "x": 3624.25,
            "y": 1753.9375
        },
        {
            "x": 3665.8125,
            "y": 1687.4375
        },
        {
            "x": 3682.4375,
            "y": 1662.5
        },
        {
            "x": 3707.375,
            "y": 1704.0625
        },
        {
            "x": 3682.4375,
            "y": 1654.1875
        },
        {
            "x": 3657.5,
            "y": 1679.125
        },
        {
            "x": 3707.375,
            "y": 1837.0625
        },
        {
            "x": 3674.125,
            "y": 1812.125
        },
        {
            "x": 3657.5,
            "y": 1812.125
        },
        {
            "x": 3649.1875,
            "y": 1787.1875
        },
        {
            "x": 3507.875,
            "y": 1953.4375
        },
        {
            "x": 3507.875,
            "y": 1970.0625
        },
        {
            "x": 3524.5,
            "y": 1970.0625
        },
        {
            "x": 2610.125,
            "y": 1163.75
        },
        {
            "x": 2917.6875,
            "y": 1537.8125
        },
        {
            "x": 2726.5,
            "y": 1188.6875
        },
        {
            "x": 2926.0,
            "y": 1554.4375
        },
        {
            "x": 2934.3125,
            "y": 1546.125
        },
        {
            "x": 2651.6875,
            "y": 1155.4375
        },
        {
            "x": 2626.75,
            "y": 1147.125
        },
        {
            "x": 2684.9375,
            "y": 1180.375
        },
        {
            "x": 2684.9375,
            "y": 1188.6875
        },
        {
            "x": 2693.25,
            "y": 1172.0625
        },
        {
            "x": 2676.625,
            "y": 1047.375
        },
        {
            "x": 2668.3125,
            "y": 1039.0625
        },
        {
            "x": 2759.75,
            "y": 1197.0
        },
        {
            "x": 2776.375,
            "y": 1205.3125
        },
        {
            "x": 2776.375,
            "y": 1221.9375
        },
        {
            "x": 2277.625,
            "y": 1163.75
        },
        {
            "x": 2660.0,
            "y": 1055.6875
        },
        {
            "x": 2626.75,
            "y": 1280.125
        },
        {
            "x": 2610.125,
            "y": 1271.8125
        },
        {
            "x": 2610.125,
            "y": 1288.4375
        },
        {
            "x": 2784.6875,
            "y": 1105.5625
        },
        {
            "x": 2776.375,
            "y": 1088.9375
        },
        {
            "x": 2801.3125,
            "y": 1113.875
        },
        {
            "x": 2734.8125,
            "y": 1305.0625
        },
        {
            "x": 2817.9375,
            "y": 1288.4375
        },
        {
            "x": 2302.5625,
            "y": 1163.75
        },
        {
            "x": 2294.25,
            "y": 1180.375
        },
        {
            "x": 3300.0625,
            "y": 947.625
        },
        {
            "x": 3283.4375,
            "y": 939.3125
        },
        {
            "x": 3300.0625,
            "y": 939.3125
        },
        {
            "x": 3283.4375,
            "y": 947.625
        },
        {
            "x": 3167.0625,
            "y": 997.5
        },
        {
            "x": 3158.75,
            "y": 1005.8125
        },
        {
            "x": 3150.4375,
            "y": 1014.125
        },
        {
            "x": 3158.75,
            "y": 864.5
        },
        {
            "x": 3175.375,
            "y": 847.875
        },
        {
            "x": 3100.5625,
            "y": 922.6875
        },
        {
            "x": 3108.875,
            "y": 914.375
        },
        {
            "x": 2801.3125,
            "y": 723.1875
        },
        {
            "x": 2809.625,
            "y": 731.5
        },
        {
            "x": 3009.125,
            "y": 615.125
        },
        {
            "x": 3042.375,
            "y": 673.3125
        },
        {
            "x": 3050.6875,
            "y": 673.3125
        },
        {
            "x": 2826.25,
            "y": 748.125
        },
        {
            "x": 3017.4375,
            "y": 590.1875
        },
        {
            "x": 3025.75,
            "y": 606.8125
        },
        {
            "x": 2784.6875,
            "y": 706.5625
        },
        {
            "x": 2959.25,
            "y": 764.75
        },
        {
            "x": 2950.9375,
            "y": 781.375
        },
        {
            "x": 3025.75,
            "y": 706.5625
        },
        {
            "x": 3017.4375,
            "y": 714.875
        },
        {
            "x": 3025.75,
            "y": 864.5
        },
        {
            "x": 3009.125,
            "y": 889.4375
        },
        {
            "x": 2992.5,
            "y": 847.875
        },
        {
            "x": 3009.125,
            "y": 897.75
        },
        {
            "x": 3034.0625,
            "y": 872.8125
        },
        {
            "x": 3092.25,
            "y": 764.75
        },
        {
            "x": 3117.1875,
            "y": 739.8125
        },
        {
            "x": 3133.8125,
            "y": 781.375
        },
        {
            "x": 3117.1875,
            "y": 731.5
        },
        {
            "x": 3083.9375,
            "y": 764.75
        },
        {
            "x": 3466.3125,
            "y": 914.375
        },
        {
            "x": 3416.4375,
            "y": 980.875
        },
        {
            "x": 3192.0,
            "y": 1180.375
        },
        {
            "x": 2984.1875,
            "y": 1180.375
        },
        {
            "x": 2984.1875,
            "y": 1172.0625
        },
        {
            "x": 2926.0,
            "y": 1113.875
        },
        {
            "x": 2917.6875,
            "y": 1105.5625
        },
        {
            "x": 2934.3125,
            "y": 1088.9375
        },
        {
            "x": 2942.625,
            "y": 1097.25
        },
        {
            "x": 3000.8125,
            "y": 1155.4375
        },
        {
            "x": 3000.8125,
            "y": 1163.75
        },
        {
            "x": 2726.5,
            "y": 889.4375
        },
        {
            "x": 2884.4375,
            "y": 457.1875
        },
        {
            "x": 2851.1875,
            "y": 523.6875
        },
        {
            "x": 2892.75,
            "y": 515.375
        },
        {
            "x": 2044.875,
            "y": 798.0
        },
        {
            "x": 2053.1875,
            "y": 781.375
        },
        {
            "x": 2136.3125,
            "y": 864.5
        },
        {
            "x": 2128.0,
            "y": 839.5625
        },
        {
            "x": 2019.9375,
            "y": 457.1875
        },
        {
            "x": 2036.5625,
            "y": 781.375
        },
        {
            "x": 1953.4375,
            "y": 631.75
        },
        {
            "x": 2028.25,
            "y": 631.75
        },
        {
            "x": 1936.8125,
            "y": 573.5625
        },
        {
            "x": 2078.125,
            "y": 814.625
        },
        {
            "x": 2036.5625,
            "y": 656.6875
        },
        {
            "x": 2053.1875,
            "y": 673.3125
        },
        {
            "x": 2078.125,
            "y": 906.0625
        },
        {
            "x": 2086.4375,
            "y": 806.3125
        },
        {
            "x": 2078.125,
            "y": 789.6875
        },
        {
            "x": 1995.0,
            "y": 673.3125
        },
        {
            "x": 2551.9375,
            "y": 590.1875
        },
        {
            "x": 2518.6875,
            "y": 598.5
        },
        {
            "x": 2709.875,
            "y": 598.5
        },
        {
            "x": 2443.875,
            "y": 598.5
        },
        {
            "x": 2635.0625,
            "y": 590.1875
        },
        {
            "x": 2261.0,
            "y": 822.9375
        },
        {
            "x": 2352.4375,
            "y": 922.6875
        },
        {
            "x": 2443.875,
            "y": 847.875
        },
        {
            "x": 2385.6875,
            "y": 814.625
        },
        {
            "x": 2435.5625,
            "y": 748.125
        },
        {
            "x": 1978.375,
            "y": 1080.625
        },
        {
            "x": 2094.75,
            "y": 515.375
        },
        {
            "x": 2128.0,
            "y": 523.6875
        },
        {
            "x": 2119.6875,
            "y": 540.3125
        },
        {
            "x": 2061.5,
            "y": 847.875
        },
        {
            "x": 2435.5625,
            "y": 773.0625
        },
        {
            "x": 2418.9375,
            "y": 756.4375
        },
        {
            "x": 2477.125,
            "y": 822.9375
        },
        {
            "x": 2468.8125,
            "y": 822.9375
        },
        {
            "x": 2443.875,
            "y": 756.4375
        },
        {
            "x": 3416.4375,
            "y": 3283.4375
        },
        {
            "x": 3399.8125,
            "y": 3300.0625
        },
        {
            "x": 3200.3125,
            "y": 3424.75
        },
        {
            "x": 3200.3125,
            "y": 3441.375
        },
        {
            "x": 3300.0625,
            "y": 3532.8125
        },
        {
            "x": 3316.6875,
            "y": 3532.8125
        },
        {
            "x": 3192.0,
            "y": 3524.5
        },
        {
            "x": 3192.0,
            "y": 3541.125
        },
        {
            "x": 3250.1875,
            "y": 3383.1875
        },
        {
            "x": 3291.75,
            "y": 3391.5
        },
        {
            "x": 3175.375,
            "y": 3458.0
        },
        {
            "x": 3308.375,
            "y": 3516.1875
        },
        {
            "x": 3150.4375,
            "y": 3449.6875
        },
        {
            "x": 3150.4375,
            "y": 3516.1875
        },
        {
            "x": 3333.3125,
            "y": 3466.3125
        },
        {
            "x": 3358.25,
            "y": 3482.9375
        },
        {
            "x": 3358.25,
            "y": 3499.5625
        },
        {
            "x": 3333.3125,
            "y": 3491.25
        },
        {
            "x": 3283.4375,
            "y": 3374.875
        },
        {
            "x": 3275.125,
            "y": 3366.5625
        },
        {
            "x": 3192.0,
            "y": 3582.6875
        },
        {
            "x": 3167.0625,
            "y": 3582.6875
        },
        {
            "x": 3491.25,
            "y": 3399.8125
        },
        {
            "x": 3491.25,
            "y": 3408.125
        },
        {
            "x": 3458.0,
            "y": 3100.5625
        },
        {
            "x": 3424.75,
            "y": 3142.125
        },
        {
            "x": 3516.1875,
            "y": 3150.4375
        },
        {
            "x": 3466.3125,
            "y": 3117.1875
        },
        {
            "x": 3441.375,
            "y": 3092.25
        },
        {
            "x": 3416.4375,
            "y": 3125.5
        },
        {
            "x": 3507.875,
            "y": 3175.375
        },
        {
            "x": 3482.9375,
            "y": 3183.6875
        },
        {
            "x": 3441.375,
            "y": 3142.125
        },
        {
            "x": 3333.3125,
            "y": 3607.625
        },
        {
            "x": 3349.9375,
            "y": 3615.9375
        },
        {
            "x": 3017.4375,
            "y": 3374.875
        },
        {
            "x": 2959.25,
            "y": 3449.6875
        },
        {
            "x": 3233.5625,
            "y": 3233.5625
        },
        {
            "x": 3241.875,
            "y": 3175.375
        },
        {
            "x": 2975.875,
            "y": 3466.3125
        },
        {
            "x": 3183.6875,
            "y": 3200.3125
        },
        {
            "x": 3408.125,
            "y": 3183.6875
        },
        {
            "x": 3391.5,
            "y": 3167.0625
        },
        {
            "x": 3482.9375,
            "y": 3059.0
        },
        {
            "x": 3507.875,
            "y": 3075.625
        },
        {
            "x": 3408.125,
            "y": 3000.8125
        },
        {
            "x": 3399.8125,
            "y": 2975.875
        },
        {
            "x": 3291.75,
            "y": 3108.875
        },
        {
            "x": 3316.6875,
            "y": 3100.5625
        },
        {
            "x": 3358.25,
            "y": 3000.8125
        },
        {
            "x": 3341.625,
            "y": 2984.1875
        },
        {
            "x": 3275.125,
            "y": 2984.1875
        },
        {
            "x": 3308.375,
            "y": 3059.0
        },
        {
            "x": 3291.75,
            "y": 3042.375
        },
        {
            "x": 3532.8125,
            "y": 3225.25
        },
        {
            "x": 3557.75,
            "y": 3192.0
        },
        {
            "x": 3133.8125,
            "y": 1363.25
        },
        {
            "x": 1961.75,
            "y": 3125.5
        },
        {
            "x": 2236.0625,
            "y": 2817.9375
        },
        {
            "x": 2211.125,
            "y": 2842.875
        },
        {
            "x": 1745.625,
            "y": 3325.0
        },
        {
            "x": 1729.0,
            "y": 3341.625
        },
        {
            "x": 3125.5,
            "y": 1371.5625
        },
        {
            "x": 1147.125,
            "y": 1945.125
        },
        {
            "x": 1138.8125,
            "y": 1961.75
        },
        {
            "x": 1155.4375,
            "y": 1953.4375
        },
        {
            "x": 1995.0,
            "y": 3100.5625
        },
        {
            "x": 2684.9375,
            "y": 1845.375
        },
        {
            "x": 2676.625,
            "y": 1820.4375
        }
    ]
}